{
  "opportunity_id": "10248",
  "prediction": {
    "predicted_outcome": "Loss",
    "actual_outcome": "Loss",
    "win_probability": 0.1320515275001526,
    "threshold": 0.2624979317188263,
    "confidence": "Low"
  },
  "key_features": {
    "customer_activity": -0.73279,
    "total_competitors": 1.0,
    "opp_quality_score": -0.3985257726988103,
    "cust_hitrate": -1.1667,
    "product_A_ratio": 0.42830306825297426
  },
  "shap_analysis": {
    "base_value": 0.06737297773361206,
    "prediction_value": -1.8829412460327148,
    "top_positive_factors": [
      {
        "feature": "contract_hitrate_ratio",
        "shap_value": 0.1792360544204712,
        "explanation": "Contract Hitrate Ratio"
      },
      {
        "feature": "opp_old",
        "shap_value": 0.10667861253023148,
        "explanation": "Antig\u00fcedad de la oportunidad"
      },
      {
        "feature": "total_past_sales",
        "shap_value": 0.04550018161535263,
        "explanation": "Volumen total de ventas hist\u00f3ricas"
      },
      {
        "feature": "opp_age_squared",
        "shap_value": 0.03170002996921539,
        "explanation": "Opp Age Squared"
      },
      {
        "feature": "product_A_recommended",
        "shap_value": 0.014514083042740822,
        "explanation": "Product A Recommended"
      }
    ],
    "top_negative_factors": [
      {
        "feature": "opp_month",
        "shap_value": -0.4182463586330414,
        "explanation": "Opp Month"
      },
      {
        "feature": "cust_hitrate",
        "shap_value": -0.3408795893192291,
        "explanation": "Tasa de \u00e9xito hist\u00f3rica con el cliente"
      },
      {
        "feature": "customer_activity",
        "shap_value": -0.3146440088748932,
        "explanation": "Nivel global de actividad del cliente"
      },
      {
        "feature": "competitor_Y",
        "shap_value": -0.294097363948822,
        "explanation": "Competitor Y"
      },
      {
        "feature": "opp_quality_score",
        "shap_value": -0.24282048642635345,
        "explanation": "Score agregado de calidad de oportunidad"
      }
    ]
  },
  "business_recommendation": {
    "action": "Re-evaluate",
    "priority": "Low",
    "next_steps": [
      "Increase touchpoints and engagement",
      "Clarify blockers with decision-makers",
      "Monitor competitive landscape and adjust pricing/offer."
    ]
  }
}