{
  "opportunity_id": "19357",
  "prediction": {
    "predicted_outcome": "Win",
    "actual_outcome": "Win",
    "win_probability": 0.8526630401611328,
    "threshold": 0.2624979317188263,
    "confidence": "High"
  },
  "key_features": {
    "customer_activity": 0.28241999999999995,
    "total_competitors": 0.0,
    "opp_quality_score": 0.5578771475953564,
    "cust_hitrate": 1.34638,
    "product_A_ratio": 0.17309286898839138
  },
  "shap_analysis": {
    "base_value": 0.06737297773361206,
    "prediction_value": 1.7556405067443848,
    "top_positive_factors": [
      {
        "feature": "product_A",
        "shap_value": 1.3922473192214966,
        "explanation": "Product A"
      },
      {
        "feature": "product_mix",
        "shap_value": 0.6760729551315308,
        "explanation": "Diversidad de productos activos"
      },
      {
        "feature": "cust_hitrate",
        "shap_value": 0.4844898283481598,
        "explanation": "Tasa de éxito histórica con el cliente"
      },
      {
        "feature": "iberia_engagement",
        "shap_value": 0.2666993737220764,
        "explanation": "Engagement de clientes de Iberia"
      },
      {
        "feature": "product_A_ratio",
        "shap_value": 0.1852189004421234,
        "explanation": "Peso de ventas históricas de Product A"
      }
    ],
    "top_negative_factors": [
      {
        "feature": "opp_quality_score",
        "shap_value": -0.5291414856910706,
        "explanation": "Score agregado de calidad de oportunidad"
      },
      {
        "feature": "cust_interactions",
        "shap_value": -0.35334742069244385,
        "explanation": "Número de interacciones con el cliente"
      },
      {
        "feature": "customer_engagement",
        "shap_value": -0.3145851492881775,
        "explanation": "Interacciones y calidad de relación con el cliente"
      },
      {
        "feature": "hitrate_contracts",
        "shap_value": -0.23594485223293304,
        "explanation": "Hitrate Contracts"
      },
      {
        "feature": "total_past_sales",
        "shap_value": -0.15237456560134888,
        "explanation": "Volumen total de ventas históricas"
      }
    ]
  },
  "business_recommendation": {
    "action": "Accelerate",
    "priority": "High",
    "next_steps": [
      {
        "step": "Conduct a thorough review of the opportunity quality score components, identifying areas needing improvement and updating the opportunity record accordingly to ensure accuracy and completeness."
      },
      {
        "step": "Schedule more frequent and higher-value interactions with the customer, focusing on addressing their specific concerns and showcasing the value proposition in a personalized manner."
      },
      {
        "step": "Implement a proactive customer engagement strategy that includes regular communication, providing relevant content and resources, and actively seeking feedback to build stronger relationships and demonstrate commitment."
      }
    ],
    "ai_generated": true
  }
}