{
  "opportunity_id": "2066",
  "prediction": {
    "predicted_outcome": "Win",
    "actual_outcome": "Loss",
    "win_probability": 0.3440251052379608,
    "threshold": 0.2624979317188263,
    "confidence": "Low"
  },
  "key_features": {
    "customer_activity": -0.5422866666666666,
    "total_competitors": 0.0,
    "opp_quality_score": -0.16992177269881026,
    "cust_hitrate": -0.59519,
    "product_A_ratio": 0.42830306825297426
  },
  "shap_analysis": {
    "base_value": 0.06737297773361206,
    "prediction_value": -0.645407497882843,
    "top_positive_factors": [
      {
        "feature": "cust_interactions",
        "shap_value": 0.20932374894618988,
        "explanation": "N\u00famero de interacciones con el cliente"
      },
      {
        "feature": "opp_month",
        "shap_value": 0.19924387335777283,
        "explanation": "Opp Month"
      },
      {
        "feature": "total_past_sales",
        "shap_value": 0.1006457507610321,
        "explanation": "Volumen total de ventas hist\u00f3ricas"
      },
      {
        "feature": "opp_old",
        "shap_value": 0.08086886256933212,
        "explanation": "Antig\u00fcedad de la oportunidad"
      },
      {
        "feature": "opp_age_squared",
        "shap_value": 0.02773892506957054,
        "explanation": "Opp Age Squared"
      }
    ],
    "top_negative_factors": [
      {
        "feature": "cust_hitrate",
        "shap_value": -0.44101378321647644,
        "explanation": "Tasa de \u00e9xito hist\u00f3rica con el cliente"
      },
      {
        "feature": "iberia_engagement",
        "shap_value": -0.30080267786979675,
        "explanation": "Engagement de clientes de Iberia"
      },
      {
        "feature": "hitrate_contracts",
        "shap_value": -0.15524522960186005,
        "explanation": "Hitrate Contracts"
      },
      {
        "feature": "product_B_sold_in_the_past",
        "shap_value": -0.10929940640926361,
        "explanation": "Product B Sold In The Past"
      },
      {
        "feature": "customer_activity",
        "shap_value": -0.10160844027996063,
        "explanation": "Nivel global de actividad del cliente"
      }
    ]
  },
  "business_recommendation": {
    "action": "Re-evaluate",
    "priority": "Low",
    "next_steps": [
      "Increase touchpoints and engagement",
      "Maintain momentum with key stakeholders",
      "Capitalize on the lack of competition to close fast."
    ]
  }
}