{
  "opportunity_id": "20956",
  "prediction": {
    "predicted_outcome": "Win",
    "actual_outcome": "Win",
    "win_probability": 0.9905201196670532,
    "threshold": 0.2624979317188263,
    "confidence": "High"
  },
  "key_features": {
    "customer_activity": 0.5536733333333334,
    "total_competitors": 2.0,
    "opp_quality_score": 0.6202902273011897,
    "cust_hitrate": 0.94289,
    "product_A_ratio": 0.42830306825297426
  },
  "shap_analysis": {
    "base_value": 0.06737297773361206,
    "prediction_value": 4.649056434631348,
    "top_positive_factors": [
      {
        "feature": "cust_hitrate",
        "shap_value": 1.0579358339309692,
        "explanation": "Tasa de \u00e9xito hist\u00f3rica con el cliente"
      },
      {
        "feature": "customer_engagement",
        "shap_value": 0.6466612815856934,
        "explanation": "Interacciones y calidad de relaci\u00f3n con el cliente"
      },
      {
        "feature": "opp_quality_score",
        "shap_value": 0.47507691383361816,
        "explanation": "Score agregado de calidad de oportunidad"
      },
      {
        "feature": "customer_activity",
        "shap_value": 0.3657822608947754,
        "explanation": "Nivel global de actividad del cliente"
      },
      {
        "feature": "competition_risk",
        "shap_value": 0.3216504156589508,
        "explanation": "Riesgo asociado a la competencia"
      }
    ],
    "top_negative_factors": [
      {
        "feature": "total_competitors",
        "shap_value": -0.13224700093269348,
        "explanation": "N\u00famero total de competidores presentes"
      },
      {
        "feature": "competitor_Y",
        "shap_value": -0.06312599778175354,
        "explanation": "Competitor Y"
      },
      {
        "feature": "product_A_ratio",
        "shap_value": -0.05721855163574219,
        "explanation": "Peso de ventas hist\u00f3ricas de Product A"
      },
      {
        "feature": "competitor_diversity",
        "shap_value": -0.02601880021393299,
        "explanation": "Diversidad de competidores en la oferta"
      },
      {
        "feature": "has_competition",
        "shap_value": -0.005019852425903082,
        "explanation": "Indicador de presencia de competencia"
      }
    ]
  },
  "business_recommendation": {
    "action": "Accelerate",
    "priority": "High",
    "next_steps": [
      "Leverage existing engagement",
      "Maintain momentum with key stakeholders",
      "Monitor competitive landscape and adjust pricing/offer."
    ]
  }
}