{
  "opportunity_id": "27196",
  "prediction": {
    "predicted_outcome": "Loss",
    "actual_outcome": "Loss",
    "win_probability": 0.09130869060754776,
    "threshold": 0.2624979317188263,
    "confidence": "Medium"
  },
  "key_features": {
    "customer_activity": -0.26059666666666664,
    "total_competitors": 1.0,
    "opp_quality_score": -0.10251477269881026,
    "cust_hitrate": -0.65219,
    "product_A_ratio": 0.42830306825297426
  },
  "shap_analysis": {
    "base_value": 0.06737297773361206,
    "prediction_value": -2.2977590560913086,
    "top_positive_factors": [
      {
        "feature": "contract_hitrate_ratio",
        "shap_value": 0.22699575126171112,
        "explanation": "Contract Hitrate Ratio"
      },
      {
        "feature": "iberia_engagement",
        "shap_value": 0.15580327808856964,
        "explanation": "Engagement de clientes de Iberia"
      },
      {
        "feature": "total_past_sales",
        "shap_value": 0.09137719124555588,
        "explanation": "Volumen total de ventas hist\u00f3ricas"
      },
      {
        "feature": "opp_old",
        "shap_value": 0.0868014544248581,
        "explanation": "Antig\u00fcedad de la oportunidad"
      },
      {
        "feature": "customer_engagement",
        "shap_value": 0.06541398912668228,
        "explanation": "Interacciones y calidad de relaci\u00f3n con el cliente"
      }
    ],
    "top_negative_factors": [
      {
        "feature": "opp_month",
        "shap_value": -1.0052398443222046,
        "explanation": "Opp Month"
      },
      {
        "feature": "cust_hitrate",
        "shap_value": -0.5187920331954956,
        "explanation": "Tasa de \u00e9xito hist\u00f3rica con el cliente"
      },
      {
        "feature": "competition_risk",
        "shap_value": -0.44695696234703064,
        "explanation": "Riesgo asociado a la competencia"
      },
      {
        "feature": "opp_quality_score",
        "shap_value": -0.28661584854125977,
        "explanation": "Score agregado de calidad de oportunidad"
      },
      {
        "feature": "hitrate_contracts",
        "shap_value": -0.21118241548538208,
        "explanation": "Hitrate Contracts"
      }
    ]
  },
  "business_recommendation": {
    "action": "Re-evaluate",
    "priority": "Low",
    "next_steps": [
      "Increase touchpoints and engagement",
      "Clarify blockers with decision-makers",
      "Monitor competitive landscape and adjust pricing/offer."
    ]
  }
}