{
  "opportunity_id": "27306",
  "prediction": {
    "predicted_outcome": "Loss",
    "actual_outcome": "Win",
    "win_probability": 0.12723462283611298,
    "threshold": 0.2624979317188263,
    "confidence": "Low"
  },
  "key_features": {
    "customer_activity": -0.20287000000000002,
    "total_competitors": 0.0,
    "opp_quality_score": -0.23954977269881028,
    "cust_hitrate": -1.1667,
    "product_A_ratio": 0.42830306825297426
  },
  "shap_analysis": {
    "base_value": 0.06737297773361206,
    "prediction_value": -1.925635576248169,
    "top_positive_factors": [
      {
        "feature": "cust_contracts",
        "shap_value": 0.10758089274168015,
        "explanation": "N\u00famero de contratos con el cliente"
      },
      {
        "feature": "opp_old",
        "shap_value": 0.1001947671175003,
        "explanation": "Antig\u00fcedad de la oportunidad"
      },
      {
        "feature": "total_past_sales",
        "shap_value": 0.0710902214050293,
        "explanation": "Volumen total de ventas hist\u00f3ricas"
      },
      {
        "feature": "competition_risk",
        "shap_value": 0.05298008397221565,
        "explanation": "Riesgo asociado a la competencia"
      },
      {
        "feature": "opp_age_squared",
        "shap_value": 0.03497416526079178,
        "explanation": "Opp Age Squared"
      }
    ],
    "top_negative_factors": [
      {
        "feature": "opp_month",
        "shap_value": -0.6794560551643372,
        "explanation": "Opp Month"
      },
      {
        "feature": "customer_activity",
        "shap_value": -0.44260498881340027,
        "explanation": "Nivel global de actividad del cliente"
      },
      {
        "feature": "iberia_engagement",
        "shap_value": -0.39163535833358765,
        "explanation": "Engagement de clientes de Iberia"
      },
      {
        "feature": "cust_hitrate",
        "shap_value": -0.33121398091316223,
        "explanation": "Tasa de \u00e9xito hist\u00f3rica con el cliente"
      },
      {
        "feature": "product_A_ratio",
        "shap_value": -0.12619023025035858,
        "explanation": "Peso de ventas hist\u00f3ricas de Product A"
      }
    ]
  },
  "business_recommendation": {
    "action": "Re-evaluate",
    "priority": "Low",
    "next_steps": [
      "Increase touchpoints and engagement",
      "Clarify blockers with decision-makers",
      "Capitalize on the lack of competition to close fast."
    ]
  }
}