{
  "opportunity_id": "28850",
  "prediction": {
    "predicted_outcome": "Win",
    "actual_outcome": "Win",
    "win_probability": 0.9764560461044312,
    "threshold": 0.31458529829978943,
    "confidence": "High"
  },
  "key_features": {
    "customer_activity": -0.02463333333333334,
    "total_competitors": 0.0,
    "opp_old": -0.28185,
    "cust_hitrate": 0.0231,
    "product_A_ratio": 0.42830306825297426
  },
  "shap_analysis": {
    "base_value": 0.0683107003569603,
    "prediction_value": 3.7250595092773438,
    "top_positive_factors": [
      {
        "feature": "contract_hitrate_ratio",
        "shap_value": 0.901786744594574,
        "explanation": "Contract Hitrate Ratio"
      },
      {
        "feature": "opp_quality_score",
        "shap_value": 0.42272698879241943,
        "explanation": "Score agregado de calidad de oportunidad"
      },
      {
        "feature": "customer_activity",
        "shap_value": 0.382499635219574,
        "explanation": "Nivel global de actividad del cliente"
      },
      {
        "feature": "customer_engagement",
        "shap_value": 0.3615179657936096,
        "explanation": "Interacciones y calidad de relaci\u00f3n con el cliente"
      },
      {
        "feature": "opp_month",
        "shap_value": 0.2951405644416809,
        "explanation": "Opp Month"
      }
    ],
    "top_negative_factors": [
      {
        "feature": "product_A_ratio",
        "shap_value": -0.05579320341348648,
        "explanation": "Peso de ventas hist\u00f3ricas de Product A"
      },
      {
        "feature": "product_A_sold_in_the_past",
        "shap_value": -0.015616076998412609,
        "explanation": "Product A Sold In The Past"
      },
      {
        "feature": "cust_contracts",
        "shap_value": -0.012085500173270702,
        "explanation": "N\u00famero de contratos con el cliente"
      },
      {
        "feature": "product_mix",
        "shap_value": -0.004950343165546656,
        "explanation": "Diversidad de productos activos"
      },
      {
        "feature": "product_A",
        "shap_value": -0.0024626392405480146,
        "explanation": "Product A"
      }
    ]
  },
  "business_recommendation": {
    "action": "Accelerate",
    "priority": "High",
    "next_steps": [
      "Leverage existing engagement",
      "Maintain momentum with key stakeholders",
      "Capitalize on the lack of competition to close fast."
    ]
  }
}