{
  "opportunity_id": "33023",
  "prediction": {
    "predicted_outcome": "Loss",
    "actual_outcome": "Loss",
    "win_probability": 0.005859979894012213,
    "threshold": 0.2624979317188263,
    "confidence": "Medium"
  },
  "key_features": {
    "customer_activity": -0.3353933333333334,
    "total_competitors": 1.0,
    "opp_quality_score": -0.6695207616834631,
    "cust_hitrate": -0.58313,
    "product_A_ratio": -0.9849094042086575
  },
  "shap_analysis": {
    "base_value": 0.06737297773361206,
    "prediction_value": -5.133729457855225,
    "top_positive_factors": [
      {
        "feature": "product_B_sold_in_the_past",
        "shap_value": 0.111721932888031,
        "explanation": "Product B Sold In The Past"
      },
      {
        "feature": "opp_old",
        "shap_value": 0.05165044590830803,
        "explanation": "Antig\u00fcedad de la oportunidad"
      },
      {
        "feature": "opp_age_squared",
        "shap_value": 0.025493785738945007,
        "explanation": "Opp Age Squared"
      },
      {
        "feature": "opp_maturity",
        "shap_value": 0.00969617161899805,
        "explanation": "Madurez de la oportunidad"
      },
      {
        "feature": "total_competitors",
        "shap_value": 0.00864113587886095,
        "explanation": "N\u00famero total de competidores presentes"
      }
    ],
    "top_negative_factors": [
      {
        "feature": "cust_hitrate",
        "shap_value": -0.8580901622772217,
        "explanation": "Tasa de \u00e9xito hist\u00f3rica con el cliente"
      },
      {
        "feature": "cust_interactions",
        "shap_value": -0.7683364152908325,
        "explanation": "N\u00famero de interacciones con el cliente"
      },
      {
        "feature": "customer_activity",
        "shap_value": -0.6514412760734558,
        "explanation": "Nivel global de actividad del cliente"
      },
      {
        "feature": "competition_risk",
        "shap_value": -0.5746058225631714,
        "explanation": "Riesgo asociado a la competencia"
      },
      {
        "feature": "opp_quality_score",
        "shap_value": -0.43670299649238586,
        "explanation": "Score agregado de calidad de oportunidad"
      }
    ]
  },
  "business_recommendation": {
    "action": "Re-evaluate",
    "priority": "Low",
    "next_steps": [
      "Increase touchpoints and engagement",
      "Clarify blockers with decision-makers",
      "Monitor competitive landscape and adjust pricing/offer."
    ]
  }
}