{
  "opportunity_id": "34652",
  "prediction": {
    "predicted_outcome": "Win",
    "actual_outcome": "Win",
    "win_probability": 0.9784672260284424,
    "threshold": 0.2624979317188263,
    "confidence": "High"
  },
  "key_features": {
    "customer_activity": -0.22146,
    "total_competitors": 1.0,
    "opp_quality_score": -0.08357568177028449,
    "cust_hitrate": -0.6978,
    "product_A_ratio": 0.4805057955742887
  },
  "shap_analysis": {
    "base_value": 0.06737297773361206,
    "prediction_value": 3.8164093494415283,
    "top_positive_factors": [
      {
        "feature": "customer_engagement",
        "shap_value": 0.5532181262969971,
        "explanation": "Interacciones y calidad de relaci\u00f3n con el cliente"
      },
      {
        "feature": "iberia_engagement",
        "shap_value": 0.5390704274177551,
        "explanation": "Engagement de clientes de Iberia"
      },
      {
        "feature": "opp_month",
        "shap_value": 0.4638232886791229,
        "explanation": "Opp Month"
      },
      {
        "feature": "contract_hitrate_ratio",
        "shap_value": 0.4300466477870941,
        "explanation": "Contract Hitrate Ratio"
      },
      {
        "feature": "total_past_sales",
        "shap_value": 0.28001487255096436,
        "explanation": "Volumen total de ventas hist\u00f3ricas"
      }
    ],
    "top_negative_factors": [
      {
        "feature": "cust_hitrate",
        "shap_value": -0.2425529956817627,
        "explanation": "Tasa de \u00e9xito hist\u00f3rica con el cliente"
      },
      {
        "feature": "competitor_Z",
        "shap_value": -0.07214350253343582,
        "explanation": "Competitor Z"
      },
      {
        "feature": "product_mix",
        "shap_value": -0.003327704733237624,
        "explanation": "Diversidad de productos activos"
      },
      {
        "feature": "product_D",
        "shap_value": -0.0026719425804913044,
        "explanation": "Product D"
      },
      {
        "feature": "product_A",
        "shap_value": -0.001398818683810532,
        "explanation": "Product A"
      }
    ]
  },
  "business_recommendation": {
    "action": "Accelerate",
    "priority": "High",
    "next_steps": [
      "Leverage existing engagement",
      "Maintain momentum with key stakeholders",
      "Monitor competitive landscape and adjust pricing/offer."
    ]
  }
}