{
  "opportunity_id": "35249",
  "prediction": {
    "predicted_outcome": "Loss",
    "actual_outcome": "Loss",
    "win_probability": 0.013684739358723164,
    "threshold": 0.2624979317188263,
    "confidence": "Medium"
  },
  "key_features": {
    "customer_activity": 0.31673333333333337,
    "total_competitors": 1.0,
    "opp_quality_score": 0.3868468214536107,
    "cust_hitrate": -0.03963,
    "product_A_ratio": 0.7592895536340267
  },
  "shap_analysis": {
    "base_value": 0.06737297773361206,
    "prediction_value": -4.277695178985596,
    "top_positive_factors": [
      {
        "feature": "customer_activity",
        "shap_value": 0.15818655490875244,
        "explanation": "Nivel global de actividad del cliente"
      },
      {
        "feature": "product_A_ratio",
        "shap_value": 0.14251090586185455,
        "explanation": "Peso de ventas hist\u00f3ricas de Product A"
      },
      {
        "feature": "cust_in_iberia",
        "shap_value": 0.12356453388929367,
        "explanation": "Cust In Iberia"
      },
      {
        "feature": "opp_old",
        "shap_value": 0.07956425100564957,
        "explanation": "Antig\u00fcedad de la oportunidad"
      },
      {
        "feature": "opp_age_squared",
        "shap_value": 0.031165044754743576,
        "explanation": "Opp Age Squared"
      }
    ],
    "top_negative_factors": [
      {
        "feature": "contract_hitrate_ratio",
        "shap_value": -0.8731702566146851,
        "explanation": "Contract Hitrate Ratio"
      },
      {
        "feature": "cust_interactions",
        "shap_value": -0.7087467908859253,
        "explanation": "N\u00famero de interacciones con el cliente"
      },
      {
        "feature": "total_past_sales",
        "shap_value": -0.6125982403755188,
        "explanation": "Volumen total de ventas hist\u00f3ricas"
      },
      {
        "feature": "customer_engagement",
        "shap_value": -0.5439285039901733,
        "explanation": "Interacciones y calidad de relaci\u00f3n con el cliente"
      },
      {
        "feature": "opp_quality_score",
        "shap_value": -0.539495050907135,
        "explanation": "Score agregado de calidad de oportunidad"
      }
    ]
  },
  "business_recommendation": {
    "action": "Re-evaluate",
    "priority": "Low",
    "next_steps": [
      "Increase touchpoints and engagement",
      "Clarify blockers with decision-makers",
      "Monitor competitive landscape and adjust pricing/offer."
    ]
  }
}