{
  "opportunity_id": "4133",
  "prediction": {
    "predicted_outcome": "Win",
    "actual_outcome": "Win",
    "win_probability": 0.9680050611495972,
    "threshold": 0.2624979317188263,
    "confidence": "High"
  },
  "key_features": {
    "customer_activity": -0.12771666666666667,
    "total_competitors": 0.0,
    "opp_quality_score": -0.048299274539113035,
    "cust_hitrate": -0.99259,
    "product_A_ratio": 0.7194818136522173
  },
  "shap_analysis": {
    "base_value": 0.06737297773361206,
    "prediction_value": 3.409658432006836,
    "top_positive_factors": [
      {
        "feature": "cust_interactions",
        "shap_value": 0.5901844501495361,
        "explanation": "N\u00famero de interacciones con el cliente"
      },
      {
        "feature": "customer_activity",
        "shap_value": 0.5374948978424072,
        "explanation": "Nivel global de actividad del cliente"
      },
      {
        "feature": "product_A_ratio",
        "shap_value": 0.533885657787323,
        "explanation": "Peso de ventas hist\u00f3ricas de Product A"
      },
      {
        "feature": "customer_engagement",
        "shap_value": 0.4515189528465271,
        "explanation": "Interacciones y calidad de relaci\u00f3n con el cliente"
      },
      {
        "feature": "iberia_engagement",
        "shap_value": 0.3876314163208008,
        "explanation": "Engagement de clientes de Iberia"
      }
    ],
    "top_negative_factors": [
      {
        "feature": "cust_hitrate",
        "shap_value": -0.7277238368988037,
        "explanation": "Tasa de \u00e9xito hist\u00f3rica con el cliente"
      },
      {
        "feature": "contract_hitrate_ratio",
        "shap_value": -0.08849327266216278,
        "explanation": "Contract Hitrate Ratio"
      },
      {
        "feature": "product_mix",
        "shap_value": -0.010788741521537304,
        "explanation": "Diversidad de productos activos"
      },
      {
        "feature": "product_A",
        "shap_value": -0.006239042151719332,
        "explanation": "Product A"
      },
      {
        "feature": "product_D",
        "shap_value": -0.0024214100558310747,
        "explanation": "Product D"
      }
    ]
  },
  "business_recommendation": {
    "action": "Accelerate",
    "priority": "High",
    "next_steps": [
      "Leverage existing engagement",
      "Maintain momentum with key stakeholders",
      "Capitalize on the lack of competition to close fast."
    ]
  }
}