{
  "opportunity_id": "5985",
  "prediction": {
    "predicted_outcome": "Loss",
    "actual_outcome": "Loss",
    "win_probability": 0.006626259535551071,
    "threshold": 0.2624979317188263,
    "confidence": "Medium"
  },
  "key_features": {
    "customer_activity": 0.16915333333333335,
    "total_competitors": 2.0,
    "opp_quality_score": 0.4425312273011897,
    "cust_hitrate": 0.73488,
    "product_A_ratio": 0.42830306825297426
  },
  "shap_analysis": {
    "base_value": 0.06737297773361206,
    "prediction_value": -5.010061740875244,
    "top_positive_factors": [
      {
        "feature": "iberia_competition",
        "shap_value": 0.07123355567455292,
        "explanation": "Competencia en clientes de Iberia"
      },
      {
        "feature": "competitor_Y",
        "shap_value": 0.05676480382680893,
        "explanation": "Competitor Y"
      },
      {
        "feature": "opp_old",
        "shap_value": 0.0549926832318306,
        "explanation": "Antig\u00fcedad de la oportunidad"
      },
      {
        "feature": "total_past_sales",
        "shap_value": 0.03494994342327118,
        "explanation": "Volumen total de ventas hist\u00f3ricas"
      },
      {
        "feature": "opp_age_squared",
        "shap_value": 0.018559571355581284,
        "explanation": "Opp Age Squared"
      }
    ],
    "top_negative_factors": [
      {
        "feature": "competition_risk",
        "shap_value": -1.1092981100082397,
        "explanation": "Riesgo asociado a la competencia"
      },
      {
        "feature": "cust_hitrate",
        "shap_value": -0.5573700070381165,
        "explanation": "Tasa de \u00e9xito hist\u00f3rica con el cliente"
      },
      {
        "feature": "competition_engagement",
        "shap_value": -0.4733574390411377,
        "explanation": "Competition Engagement"
      },
      {
        "feature": "opp_quality_score",
        "shap_value": -0.4603673219680786,
        "explanation": "Score agregado de calidad de oportunidad"
      },
      {
        "feature": "customer_engagement",
        "shap_value": -0.4572578966617584,
        "explanation": "Interacciones y calidad de relaci\u00f3n con el cliente"
      }
    ]
  },
  "business_recommendation": {
    "action": "Re-evaluate",
    "priority": "Low",
    "next_steps": [
      "Increase touchpoints and engagement",
      "Clarify blockers with decision-makers",
      "Monitor competitive landscape and adjust pricing/offer."
    ]
  }
}