{
  "opportunity_id": "6958",
  "prediction": {
    "predicted_outcome": "Loss",
    "actual_outcome": "Win",
    "win_probability": 0.10788978636264801,
    "threshold": 0.31458529829978943,
    "confidence": "High"
  },
  "key_features": {
    "customer_activity": -0.6784500000000001,
    "total_competitors": 1.0,
    "opp_old": -0.28185,
    "cust_hitrate": -1.1667,
    "product_A_ratio": 0.42830306825297426
  },
  "shap_analysis": {
    "base_value": 0.0683107003569603,
    "prediction_value": -2.1124792098999023,
    "top_positive_factors": [
      {
        "feature": "contract_hitrate_ratio",
        "shap_value": 0.19491952657699585,
        "explanation": "Contract Hitrate Ratio"
      },
      {
        "feature": "opp_old",
        "shap_value": 0.10431409627199173,
        "explanation": "Antig\u00fcedad de la oportunidad"
      },
      {
        "feature": "product_A_recommended",
        "shap_value": 0.02133944071829319,
        "explanation": "Product A Recommended"
      },
      {
        "feature": "opp_age_squared",
        "shap_value": 0.0176275372505188,
        "explanation": "Opp Age Squared"
      },
      {
        "feature": "competitor_diversity",
        "shap_value": 0.0025923210196197033,
        "explanation": "Diversidad de competidores en la oferta"
      }
    ],
    "top_negative_factors": [
      {
        "feature": "opp_month",
        "shap_value": -0.2911562919616699,
        "explanation": "Opp Month"
      },
      {
        "feature": "cust_hitrate",
        "shap_value": -0.2752339243888855,
        "explanation": "Tasa de \u00e9xito hist\u00f3rica con el cliente"
      },
      {
        "feature": "customer_activity",
        "shap_value": -0.2665955722332001,
        "explanation": "Nivel global de actividad del cliente"
      },
      {
        "feature": "cust_interactions",
        "shap_value": -0.23937232792377472,
        "explanation": "N\u00famero de interacciones con el cliente"
      },
      {
        "feature": "opp_quality_score",
        "shap_value": -0.21516457200050354,
        "explanation": "Score agregado de calidad de oportunidad"
      }
    ]
  },
  "business_recommendation": {
    "action": "Re-evaluate",
    "priority": "Low",
    "next_steps": [
      "Increase touchpoints and engagement",
      "Clarify blockers with decision-makers",
      "Monitor competitive landscape and adjust pricing/offer."
    ]
  }
}